tracardi_pushover_webhook/plugin.py
tracardi_pushover_webhook/model/pushover_config.py
tracardi_pushover_webhook/model/__pycache__/pushover_config.cpython-38.pyc
tracardi_pushover_webhook/tests/test_plugin.py
tracardi_pushover_webhook-0.6.0.dist-info/LICENSE.md
tracardi_pushover_webhook-0.6.0.dist-info/METADATA
tracardi_pushover_webhook-0.6.0.dist-info/WHEEL
tracardi_pushover_webhook-0.6.0.dist-info/top_level.txt
tracardi_pushover_webhook-0.6.0.dist-info/RECORD
