Metadata-Version: 2.1
Name: tracardi-pushover-webhook
Version: 0.6.0
Summary: This plugin connects with pushover app and sends message.
Home-page: UNKNOWN
Author: Bartosz Dobrosielski, Risto Kowaczewski
Author-email: bdobrosielski@edu.cdv.pl
License: UNKNOWN
Keywords: tracardi,plugin
Platform: UNKNOWN
Classifier: Programming Language :: Python :: 3
Classifier: License :: OSI Approved :: MIT License
Classifier: Operating System :: OS Independent
Requires-Python: >=3.8
License-File: LICENSE.md
Requires-Dist: pydantic
Requires-Dist: tracardi-plugin-sdk (>=0.6.22)
Requires-Dist: tracardi
Requires-Dist: aiohttp
Requires-Dist: urllib3
